{
  "album": "6iVod7sxHuuTW9r76ixn12",
  "albumName": "ark",
  "id": "2QCn0AZR9MBdAflIcJnU4a",
  "name": "Larva",
  "track_number": 6,
  "features_url": "https://api.spotify.com/v1/audio-features/2QCn0AZR9MBdAflIcJnU4a",
  "uri": "spotify:track:2QCn0AZR9MBdAflIcJnU4a",
  "danceability": 0.743,
  "energy": 0.888,
  "key": 10,
  "loudness": -9.438,
  "mode": 0,
  "speechiness": 0.0934,
  "acousticness": 0.0000297,
  "instrumentalness": 0.921,
  "liveness": 0.541,
  "valence": 0.869,
  "tempo": 145.992,
  "type": "audio_features",
  "track_href": "https://api.spotify.com/v1/tracks/2QCn0AZR9MBdAflIcJnU4a",
  "analysis_url": "https://api.spotify.com/v1/audio-analysis/2QCn0AZR9MBdAflIcJnU4a",
  "duration_ms": 235267,
  "time_signature": 4,
  "keyName": "Gm"
}