{
  "album": "1Z7cf3w7i7HNOdx3ljZCIP",
  "albumName": "Tierra",
  "id": "5CKQd1N48srNAyca4cnGHK",
  "name": "Inner Core",
  "track_number": 6,
  "features_url": "https://api.spotify.com/v1/audio-features/5CKQd1N48srNAyca4cnGHK",
  "uri": "spotify:track:5CKQd1N48srNAyca4cnGHK",
  "danceability": 0.469,
  "energy": 0.921,
  "key": 7,
  "loudness": -6.275,
  "mode": 1,
  "speechiness": 0.062,
  "acousticness": 0.000636,
  "instrumentalness": 0.0192,
  "liveness": 0.364,
  "valence": 0.429,
  "tempo": 92.029,
  "type": "audio_features",
  "track_href": "https://api.spotify.com/v1/tracks/5CKQd1N48srNAyca4cnGHK",
  "analysis_url": "https://api.spotify.com/v1/audio-analysis/5CKQd1N48srNAyca4cnGHK",
  "duration_ms": 331267,
  "time_signature": 4,
  "keyName": "G"
}