{
  "album": "3XOXoFkYukzqWqYI1tFcs7",
  "albumName": "QUADRINITY+MEMBER+S+BEST+SELECTIONS",
  "id": "2DBmO2pYEQWWvEsqW2fTlD",
  "name": "get out from the shell -asian Version",
  "track_number": 4,
  "features_url": "https://api.spotify.com/v1/audio-features/2DBmO2pYEQWWvEsqW2fTlD",
  "uri": "spotify:track:2DBmO2pYEQWWvEsqW2fTlD",
  "danceability": 0.555,
  "energy": 0.836,
  "key": 5,
  "loudness": -4.885,
  "mode": 0,
  "speechiness": 0.12,
  "acousticness": 0.000244,
  "instrumentalness": 0.000284,
  "liveness": 0.271,
  "valence": 0.393,
  "tempo": 138.099,
  "type": "audio_features",
  "track_href": "https://api.spotify.com/v1/tracks/2DBmO2pYEQWWvEsqW2fTlD",
  "analysis_url": "https://api.spotify.com/v1/audio-analysis/2DBmO2pYEQWWvEsqW2fTlD",
  "duration_ms": 255787,
  "time_signature": 4,
  "keyName": "Dm"
}