{
  "album": "45IByWn7b2KKHpBQ38KRFl",
  "albumName": "Clicked+Singles+Best+13",
  "id": "41U2yNryj4A4uXkhBjcPkd",
  "name": "NEO UNIVERSE",
  "track_number": 11,
  "features_url": "https://api.spotify.com/v1/audio-features/41U2yNryj4A4uXkhBjcPkd",
  "uri": "spotify:track:41U2yNryj4A4uXkhBjcPkd",
  "danceability": 0.528,
  "energy": 0.849,
  "key": 6,
  "loudness": -6.18,
  "mode": 1,
  "speechiness": 0.0291,
  "acousticness": 0.000245,
  "instrumentalness": 0.0000435,
  "liveness": 0.409,
  "valence": 0.483,
  "tempo": 114.936,
  "type": "audio_features",
  "track_href": "https://api.spotify.com/v1/tracks/41U2yNryj4A4uXkhBjcPkd",
  "analysis_url": "https://api.spotify.com/v1/audio-analysis/41U2yNryj4A4uXkhBjcPkd",
  "duration_ms": 249000,
  "time_signature": 4,
  "keyName": "F#/Gb"
}