{
  "album": "3Gl695C7JIm6L7r9l11UWm",
  "albumName": "Withering+to+Death",
  "id": "1E06UTlQzhy2LhUkKC2qcb",
  "name": "Kodoku ni shisu, yueni kodoku",
  "track_number": 4,
  "features_url": "https://api.spotify.com/v1/audio-features/1E06UTlQzhy2LhUkKC2qcb",
  "uri": "spotify:track:1E06UTlQzhy2LhUkKC2qcb",
  "danceability": 0.391,
  "energy": 0.783,
  "key": 6,
  "loudness": -8.016,
  "mode": 0,
  "speechiness": 0.0417,
  "acousticness": 0.0000186,
  "instrumentalness": 0.145,
  "liveness": 0.0679,
  "valence": 0.324,
  "tempo": 131.995,
  "type": "audio_features",
  "track_href": "https://api.spotify.com/v1/tracks/1E06UTlQzhy2LhUkKC2qcb",
  "analysis_url": "https://api.spotify.com/v1/audio-analysis/1E06UTlQzhy2LhUkKC2qcb",
  "duration_ms": 205800,
  "time_signature": 4,
  "keyName": "D#/Ebm"
}