{
  "album": "6I8TaPQwzMpSEyt1DvhUwF",
  "albumName": "SMILE",
  "id": "5sOoJ4pdoeJZyNHjAHJBmr",
  "name": "Kuchizuke",
  "track_number": 1,
  "features_url": "https://api.spotify.com/v1/audio-features/5sOoJ4pdoeJZyNHjAHJBmr",
  "uri": "spotify:track:5sOoJ4pdoeJZyNHjAHJBmr",
  "danceability": 0.463,
  "energy": 0.933,
  "key": 9,
  "loudness": -5.023,
  "mode": 0,
  "speechiness": 0.0392,
  "acousticness": 0.00517,
  "instrumentalness": 0.000182,
  "liveness": 0.0989,
  "valence": 0.452,
  "tempo": 91.991,
  "type": "audio_features",
  "track_href": "https://api.spotify.com/v1/tracks/5sOoJ4pdoeJZyNHjAHJBmr",
  "analysis_url": "https://api.spotify.com/v1/audio-analysis/5sOoJ4pdoeJZyNHjAHJBmr",
  "duration_ms": 264667,
  "time_signature": 4,
  "keyName": "F#m"
}