{
  "album": "6d3vN0L2lzLvtET3zVufMM",
  "albumName": "瞳の住人",
  "id": "3VaomYrJueQDNSQYGgWPIx",
  "name": "READY STEADY GO (tetsu READY)",
  "track_number": 4,
  "features_url": "https://api.spotify.com/v1/audio-features/3VaomYrJueQDNSQYGgWPIx",
  "uri": "spotify:track:3VaomYrJueQDNSQYGgWPIx",
  "danceability": 0.558,
  "energy": 0.966,
  "key": 1,
  "loudness": -3.548,
  "mode": 1,
  "speechiness": 0.0544,
  "acousticness": 0.00279,
  "instrumentalness": 0.00000863,
  "liveness": 0.262,
  "valence": 0.818,
  "tempo": 144.037,
  "type": "audio_features",
  "track_href": "https://api.spotify.com/v1/tracks/3VaomYrJueQDNSQYGgWPIx",
  "analysis_url": "https://api.spotify.com/v1/audio-analysis/3VaomYrJueQDNSQYGgWPIx",
  "duration_ms": 227773,
  "time_signature": 4,
  "keyName": "C#/Db"
}