{
  "album": "3GhPRWkbVLzrPxZs1QpbWt",
  "albumName": "Jojoushi",
  "id": "56W7i0d1A1ktYMyj8MR6On",
  "name": "HEAVEN'S DRIVE 2005 - TETSU P'UNKless Version",
  "track_number": 4,
  "features_url": "https://api.spotify.com/v1/audio-features/56W7i0d1A1ktYMyj8MR6On",
  "uri": "spotify:track:56W7i0d1A1ktYMyj8MR6On",
  "danceability": 0.429,
  "energy": 0.956,
  "key": 2,
  "loudness": -6.16,
  "mode": 1,
  "speechiness": 0.0354,
  "acousticness": 0.0000174,
  "instrumentalness": 0.559,
  "liveness": 0.0828,
  "valence": 0.824,
  "tempo": 141.973,
  "type": "audio_features",
  "track_href": "https://api.spotify.com/v1/tracks/56W7i0d1A1ktYMyj8MR6On",
  "analysis_url": "https://api.spotify.com/v1/audio-analysis/56W7i0d1A1ktYMyj8MR6On",
  "duration_ms": 227933,
  "time_signature": 4,
  "keyName": "D"
}