{
  "album": "24dLT7T5xA1qYcZXuo7lQR",
  "albumName": "HONEY",
  "id": "1NBUVE4t2cMjTOpEKtRnaW",
  "name": "HONEY",
  "track_number": 1,
  "features_url": "https://api.spotify.com/v1/audio-features/1NBUVE4t2cMjTOpEKtRnaW",
  "uri": "spotify:track:1NBUVE4t2cMjTOpEKtRnaW",
  "danceability": 0.333,
  "energy": 0.949,
  "key": 5,
  "loudness": -3.897,
  "mode": 1,
  "speechiness": 0.0627,
  "acousticness": 0.000801,
  "instrumentalness": 0.0000165,
  "liveness": 0.233,
  "valence": 0.321,
  "tempo": 91.393,
  "type": "audio_features",
  "track_href": "https://api.spotify.com/v1/tracks/1NBUVE4t2cMjTOpEKtRnaW",
  "analysis_url": "https://api.spotify.com/v1/audio-analysis/1NBUVE4t2cMjTOpEKtRnaW",
  "duration_ms": 227000,
  "time_signature": 4,
  "keyName": "F"
}