{
  "album": "20MoIF4GQlklB7nWhdtDip",
  "albumName": "VORTEX",
  "id": "3Ri7l3PHHAsOBCncizuZwz",
  "name": "UNCERTAIN SENSE",
  "track_number": 2,
  "features_url": "https://api.spotify.com/v1/audio-features/3Ri7l3PHHAsOBCncizuZwz",
  "uri": "spotify:track:3Ri7l3PHHAsOBCncizuZwz",
  "danceability": 0.55,
  "energy": 0.925,
  "key": 7,
  "loudness": -4.431,
  "mode": 1,
  "speechiness": 0.0999,
  "acousticness": 0.00000866,
  "instrumentalness": 0.0000514,
  "liveness": 0.345,
  "valence": 0.517,
  "tempo": 119.969,
  "type": "audio_features",
  "track_href": "https://api.spotify.com/v1/tracks/3Ri7l3PHHAsOBCncizuZwz",
  "analysis_url": "https://api.spotify.com/v1/audio-analysis/3Ri7l3PHHAsOBCncizuZwz",
  "duration_ms": 206200,
  "time_signature": 4,
  "keyName": "G"
}