{
  "album": "53htE9F7Jnz946GjnMF5bT",
  "albumName": "ectomorphed+works",
  "id": "7h8CcdQZFqpGquXmyj1FAq",
  "name": "Shinshoku -lose control - ectoborn mix",
  "track_number": 5,
  "features_url": "https://api.spotify.com/v1/audio-features/7h8CcdQZFqpGquXmyj1FAq",
  "uri": "spotify:track:7h8CcdQZFqpGquXmyj1FAq",
  "danceability": 0.454,
  "energy": 0.796,
  "key": 11,
  "loudness": -9.183,
  "mode": 0,
  "speechiness": 0.0426,
  "acousticness": 0.00000263,
  "instrumentalness": 0.856,
  "liveness": 0.0472,
  "valence": 0.392,
  "tempo": 159.994,
  "type": "audio_features",
  "track_href": "https://api.spotify.com/v1/tracks/7h8CcdQZFqpGquXmyj1FAq",
  "analysis_url": "https://api.spotify.com/v1/audio-analysis/7h8CcdQZFqpGquXmyj1FAq",
  "duration_ms": 358733,
  "time_signature": 4,
  "keyName": "G#m"
}