{
  "album": "0Aw5UHqjaiGmLUNE6ZnYkU",
  "albumName": "Uroboros+with+the+proof+in+the+name+of+living+",
  "id": "71sl6NDlSuGtiAXBMMEoGj",
  "name": "Hydra -666-",
  "track_number": 5,
  "features_url": "https://api.spotify.com/v1/audio-features/71sl6NDlSuGtiAXBMMEoGj",
  "uri": "spotify:track:71sl6NDlSuGtiAXBMMEoGj",
  "danceability": 0.383,
  "energy": 0.96,
  "key": 1,
  "loudness": -4.032,
  "mode": 1,
  "speechiness": 0.0692,
  "acousticness": 0.0000855,
  "instrumentalness": 0.397,
  "liveness": 0.202,
  "valence": 0.201,
  "tempo": 150.207,
  "type": "audio_features",
  "track_href": "https://api.spotify.com/v1/tracks/71sl6NDlSuGtiAXBMMEoGj",
  "analysis_url": "https://api.spotify.com/v1/audio-analysis/71sl6NDlSuGtiAXBMMEoGj",
  "duration_ms": 219680,
  "time_signature": 4,
  "keyName": "C#/Db"
}