{
  "album_type": "single",
  "artists": [
    {
      "external_urls": {
        "spotify": "https://open.spotify.com/artist/6jTjjAjvYvMYfaqi837p5x"
      },
      "href": "https://api.spotify.com/v1/artists/6jTjjAjvYvMYfaqi837p5x",
      "id": "6jTjjAjvYvMYfaqi837p5x",
      "name": "L'Arc-en-Ciel",
      "type": "artist",
      "uri": "spotify:artist:6jTjjAjvYvMYfaqi837p5x"
    }
  ],
  "available_markets": [
    "AD",
    "AE",
    "AR",
    "AT",
    "AU",
    "BE",
    "BG",
    "BH",
    "BO",
    "BR",
    "CA",
    "CH",
    "CL",
    "CO",
    "CR",
    "CY",
    "CZ",
    "DE",
    "DK",
    "DO",
    "DZ",
    "EC",
    "EE",
    "EG",
    "ES",
    "FI",
    "FR",
    "GB",
    "GR",
    "GT",
    "HK",
    "HN",
    "HU",
    "ID",
    "IE",
    "IL",
    "IN",
    "IS",
    "IT",
    "JO",
    "KW",
    "LB",
    "LI",
    "LT",
    "LU",
    "LV",
    "MA",
    "MC",
    "MT",
    "MX",
    "MY",
    "NI",
    "NL",
    "NO",
    "NZ",
    "OM",
    "PA",
    "PE",
    "PH",
    "PL",
    "PS",
    "PT",
    "PY",
    "QA",
    "RO",
    "SA",
    "SE",
    "SG",
    "SK",
    "SV",
    "TH",
    "TN",
    "TR",
    "TW",
    "US",
    "UY",
    "VN",
    "ZA"
  ],
  "copyrights": [
    {
      "text": "(P) 2007 Sony Music Labels Inc.",
      "type": "P"
    }
  ],
  "external_ids": {
    "upc": "886448170235"
  },
  "external_urls": {
    "spotify": "https://open.spotify.com/album/48jtqmn01LmQC7JHExPKJc"
  },
  "genres": [],
  "href": "https://api.spotify.com/v1/albums/48jtqmn01LmQC7JHExPKJc",
  "id": "48jtqmn01LmQC7JHExPKJc",
  "images": [
    {
      "height": 640,
      "url": "https://i.scdn.co/image/ab67616d0000b27358c7a27d8ca92d0e999aae8e",
      "width": 640
    },
    {
      "height": 300,
      "url": "https://i.scdn.co/image/ab67616d00001e0258c7a27d8ca92d0e999aae8e",
      "width": 300
    },
    {
      "height": 64,
      "url": "https://i.scdn.co/image/ab67616d0000485158c7a27d8ca92d0e999aae8e",
      "width": 64
    }
  ],
  "label": "Sony Music Labels Inc.",
  "name": "SEVENTH HEAVEN",
  "popularity": 5,
  "release_date": "2007-05-30",
  "release_date_precision": "day",
  "total_tracks": 4,
  "tracks": {
    "href": "https://api.spotify.com/v1/albums/48jtqmn01LmQC7JHExPKJc/tracks?offset=0&limit=50",
    "items": [
      {
        "artists": [
          {
            "external_urls": {
              "spotify": "https://open.spotify.com/artist/6jTjjAjvYvMYfaqi837p5x"
            },
            "href": "https://api.spotify.com/v1/artists/6jTjjAjvYvMYfaqi837p5x",
            "id": "6jTjjAjvYvMYfaqi837p5x",
            "name": "L'Arc-en-Ciel",
            "type": "artist",
            "uri": "spotify:artist:6jTjjAjvYvMYfaqi837p5x"
          }
        ],
        "available_markets": [
          "AD",
          "AE",
          "AR",
          "AT",
          "AU",
          "BE",
          "BG",
          "BH",
          "BO",
          "BR",
          "CA",
          "CH",
          "CL",
          "CO",
          "CR",
          "CY",
          "CZ",
          "DE",
          "DK",
          "DO",
          "DZ",
          "EC",
          "EE",
          "EG",
          "ES",
          "FI",
          "FR",
          "GB",
          "GR",
          "GT",
          "HK",
          "HN",
          "HU",
          "ID",
          "IE",
          "IL",
          "IN",
          "IS",
          "IT",
          "JO",
          "KW",
          "LB",
          "LI",
          "LT",
          "LU",
          "LV",
          "MA",
          "MC",
          "MT",
          "MX",
          "MY",
          "NI",
          "NL",
          "NO",
          "NZ",
          "OM",
          "PA",
          "PE",
          "PH",
          "PL",
          "PS",
          "PT",
          "PY",
          "QA",
          "RO",
          "SA",
          "SE",
          "SG",
          "SK",
          "SV",
          "TH",
          "TN",
          "TR",
          "TW",
          "US",
          "UY",
          "VN",
          "ZA"
        ],
        "disc_number": 1,
        "duration_ms": 302320,
        "explicit": false,
        "external_urls": {
          "spotify": "https://open.spotify.com/track/0NmMZQpcU4BjxyEFNurwTW"
        },
        "href": "https://api.spotify.com/v1/tracks/0NmMZQpcU4BjxyEFNurwTW",
        "id": "0NmMZQpcU4BjxyEFNurwTW",
        "is_local": false,
        "name": "SEVENTH HEAVEN",
        "preview_url": "https://p.scdn.co/mp3-preview/79c599f7916f639f57a7fcfbff6e139d4a94df81?cid=b7571c1e287b48d5865c4b6cc0380daa",
        "track_number": 1,
        "type": "track",
        "uri": "spotify:track:0NmMZQpcU4BjxyEFNurwTW"
      },
      {
        "artists": [
          {
            "external_urls": {
              "spotify": "https://open.spotify.com/artist/3zCyKFmflQ1bZEg7KhjeI9"
            },
            "href": "https://api.spotify.com/v1/artists/3zCyKFmflQ1bZEg7KhjeI9",
            "id": "3zCyKFmflQ1bZEg7KhjeI9",
            "name": "P'UNK～EN～CIEL",
            "type": "artist",
            "uri": "spotify:artist:3zCyKFmflQ1bZEg7KhjeI9"
          }
        ],
        "available_markets": [
          "AD",
          "AE",
          "AR",
          "AT",
          "AU",
          "BE",
          "BG",
          "BH",
          "BO",
          "BR",
          "CA",
          "CH",
          "CL",
          "CO",
          "CR",
          "CY",
          "CZ",
          "DE",
          "DK",
          "DO",
          "DZ",
          "EC",
          "EE",
          "EG",
          "ES",
          "FI",
          "FR",
          "GB",
          "GR",
          "GT",
          "HK",
          "HN",
          "HU",
          "ID",
          "IE",
          "IL",
          "IN",
          "IS",
          "IT",
          "JO",
          "KW",
          "LB",
          "LI",
          "LT",
          "LU",
          "LV",
          "MA",
          "MC",
          "MT",
          "MX",
          "MY",
          "NI",
          "NL",
          "NO",
          "NZ",
          "OM",
          "PA",
          "PE",
          "PH",
          "PL",
          "PS",
          "PT",
          "PY",
          "QA",
          "RO",
          "SA",
          "SE",
          "SG",
          "SK",
          "SV",
          "TH",
          "TN",
          "TR",
          "TW",
          "US",
          "UY",
          "VN",
          "ZA"
        ],
        "disc_number": 1,
        "duration_ms": 222213,
        "explicit": false,
        "external_urls": {
          "spotify": "https://open.spotify.com/track/7G4U7jBcU6m6jwVaCzMO7o"
        },
        "href": "https://api.spotify.com/v1/tracks/7G4U7jBcU6m6jwVaCzMO7o",
        "id": "7G4U7jBcU6m6jwVaCzMO7o",
        "is_local": false,
        "name": "HONEY 2007",
        "preview_url": "https://p.scdn.co/mp3-preview/ecf41a4bad40560f853f4ea21df3be639775f48f?cid=b7571c1e287b48d5865c4b6cc0380daa",
        "track_number": 2,
        "type": "track",
        "uri": "spotify:track:7G4U7jBcU6m6jwVaCzMO7o"
      },
      {
        "artists": [
          {
            "external_urls": {
              "spotify": "https://open.spotify.com/artist/6jTjjAjvYvMYfaqi837p5x"
            },
            "href": "https://api.spotify.com/v1/artists/6jTjjAjvYvMYfaqi837p5x",
            "id": "6jTjjAjvYvMYfaqi837p5x",
            "name": "L'Arc-en-Ciel",
            "type": "artist",
            "uri": "spotify:artist:6jTjjAjvYvMYfaqi837p5x"
          }
        ],
        "available_markets": [
          "AD",
          "AE",
          "AR",
          "AT",
          "AU",
          "BE",
          "BG",
          "BH",
          "BO",
          "BR",
          "CA",
          "CH",
          "CL",
          "CO",
          "CR",
          "CY",
          "CZ",
          "DE",
          "DK",
          "DO",
          "DZ",
          "EC",
          "EE",
          "EG",
          "ES",
          "FI",
          "FR",
          "GB",
          "GR",
          "GT",
          "HK",
          "HN",
          "HU",
          "ID",
          "IE",
          "IL",
          "IN",
          "IS",
          "IT",
          "JO",
          "KW",
          "LB",
          "LI",
          "LT",
          "LU",
          "LV",
          "MA",
          "MC",
          "MT",
          "MX",
          "MY",
          "NI",
          "NL",
          "NO",
          "NZ",
          "OM",
          "PA",
          "PE",
          "PH",
          "PL",
          "PS",
          "PT",
          "PY",
          "QA",
          "RO",
          "SA",
          "SE",
          "SG",
          "SK",
          "SV",
          "TH",
          "TN",
          "TR",
          "TW",
          "US",
          "UY",
          "VN",
          "ZA"
        ],
        "disc_number": 1,
        "duration_ms": 304306,
        "explicit": false,
        "external_urls": {
          "spotify": "https://open.spotify.com/track/7Hhx084W6A6zbAehioacTq"
        },
        "href": "https://api.spotify.com/v1/tracks/7Hhx084W6A6zbAehioacTq",
        "id": "7Hhx084W6A6zbAehioacTq",
        "is_local": false,
        "name": "SEVENTH HEAVEN - hydeless Version",
        "preview_url": "https://p.scdn.co/mp3-preview/f947d760a2e03c06e61f5fb31353cb09cce28c96?cid=b7571c1e287b48d5865c4b6cc0380daa",
        "track_number": 3,
        "type": "track",
        "uri": "spotify:track:7Hhx084W6A6zbAehioacTq"
      },
      {
        "artists": [
          {
            "external_urls": {
              "spotify": "https://open.spotify.com/artist/3zCyKFmflQ1bZEg7KhjeI9"
            },
            "href": "https://api.spotify.com/v1/artists/3zCyKFmflQ1bZEg7KhjeI9",
            "id": "3zCyKFmflQ1bZEg7KhjeI9",
            "name": "P'UNK～EN～CIEL",
            "type": "artist",
            "uri": "spotify:artist:3zCyKFmflQ1bZEg7KhjeI9"
          }
        ],
        "available_markets": [
          "AD",
          "AE",
          "AR",
          "AT",
          "AU",
          "BE",
          "BG",
          "BH",
          "BO",
          "BR",
          "CA",
          "CH",
          "CL",
          "CO",
          "CR",
          "CY",
          "CZ",
          "DE",
          "DK",
          "DO",
          "DZ",
          "EC",
          "EE",
          "EG",
          "ES",
          "FI",
          "FR",
          "GB",
          "GR",
          "GT",
          "HK",
          "HN",
          "HU",
          "ID",
          "IE",
          "IL",
          "IN",
          "IS",
          "IT",
          "JO",
          "KW",
          "LB",
          "LI",
          "LT",
          "LU",
          "LV",
          "MA",
          "MC",
          "MT",
          "MX",
          "MY",
          "NI",
          "NL",
          "NO",
          "NZ",
          "OM",
          "PA",
          "PE",
          "PH",
          "PL",
          "PS",
          "PT",
          "PY",
          "QA",
          "RO",
          "SA",
          "SE",
          "SG",
          "SK",
          "SV",
          "TH",
          "TN",
          "TR",
          "TW",
          "US",
          "UY",
          "VN",
          "ZA"
        ],
        "disc_number": 1,
        "duration_ms": 222213,
        "explicit": false,
        "external_urls": {
          "spotify": "https://open.spotify.com/track/4TnhwklMMaJBFCiA1pSSmS"
        },
        "href": "https://api.spotify.com/v1/tracks/4TnhwklMMaJBFCiA1pSSmS",
        "id": "4TnhwklMMaJBFCiA1pSSmS",
        "is_local": false,
        "name": "HONEY 2007 - TETSU P'UNKless Version",
        "preview_url": "https://p.scdn.co/mp3-preview/b2e9e02cfd701a49d654664bce7c04ca96840528?cid=b7571c1e287b48d5865c4b6cc0380daa",
        "track_number": 4,
        "type": "track",
        "uri": "spotify:track:4TnhwklMMaJBFCiA1pSSmS"
      }
    ],
    "limit": 50,
    "next": null,
    "offset": 0,
    "previous": null,
    "total": 4
  },
  "type": "album",
  "uri": "spotify:album:48jtqmn01LmQC7JHExPKJc"
}