{
  "album": "7ycgkWOb2Ri0dm1GKlaQw6",
  "albumName": "TWENITY+1997+1999",
  "id": "2zddk996mQGvI21jmxR8yS",
  "name": "あなた",
  "track_number": 6,
  "features_url": "https://api.spotify.com/v1/audio-features/2zddk996mQGvI21jmxR8yS",
  "uri": "spotify:track:2zddk996mQGvI21jmxR8yS",
  "danceability": 0.354,
  "energy": 0.746,
  "key": 7,
  "loudness": -4.429,
  "mode": 1,
  "speechiness": 0.0389,
  "acousticness": 0.251,
  "instrumentalness": 0,
  "liveness": 0.18,
  "valence": 0.372,
  "tempo": 74.739,
  "type": "audio_features",
  "track_href": "https://api.spotify.com/v1/tracks/2zddk996mQGvI21jmxR8yS",
  "analysis_url": "https://api.spotify.com/v1/audio-analysis/2zddk996mQGvI21jmxR8yS",
  "duration_ms": 321067,
  "time_signature": 4,
  "keyName": "G"
}