{
  "album": "4GgNQ1L7gElMpBini9HbpY",
  "albumName": "Withering+To+Death+",
  "id": "2OAcctY6qpR3e7OOHAYwAU",
  "name": "Garbage",
  "track_number": 7,
  "features_url": "https://api.spotify.com/v1/audio-features/2OAcctY6qpR3e7OOHAYwAU",
  "uri": "spotify:track:2OAcctY6qpR3e7OOHAYwAU",
  "danceability": 0.448,
  "energy": 0.876,
  "key": 8,
  "loudness": -6.904,
  "mode": 1,
  "speechiness": 0.0834,
  "acousticness": 0.00000199,
  "instrumentalness": 0.00000174,
  "liveness": 0.278,
  "valence": 0.459,
  "tempo": 92.975,
  "type": "audio_features",
  "track_href": "https://api.spotify.com/v1/tracks/2OAcctY6qpR3e7OOHAYwAU",
  "analysis_url": "https://api.spotify.com/v1/audio-analysis/2OAcctY6qpR3e7OOHAYwAU",
  "duration_ms": 168707,
  "time_signature": 4,
  "keyName": "Ab"
}