{
  "album": "6CkYdkJDxvXAfcnN7gj02O",
  "albumName": "Vulgar",
  "id": "1UEf8AErBRG2DYnkGheA30",
  "name": "Asunaki koufuku, koenaki asu",
  "track_number": 7,
  "features_url": "https://api.spotify.com/v1/audio-features/1UEf8AErBRG2DYnkGheA30",
  "uri": "spotify:track:1UEf8AErBRG2DYnkGheA30",
  "danceability": 0.469,
  "energy": 0.974,
  "key": 5,
  "loudness": -5.821,
  "mode": 0,
  "speechiness": 0.133,
  "acousticness": 0.0000016,
  "instrumentalness": 0.0138,
  "liveness": 0.327,
  "valence": 0.136,
  "tempo": 107.99,
  "type": "audio_features",
  "track_href": "https://api.spotify.com/v1/tracks/1UEf8AErBRG2DYnkGheA30",
  "analysis_url": "https://api.spotify.com/v1/audio-analysis/1UEf8AErBRG2DYnkGheA30",
  "duration_ms": 211147,
  "time_signature": 4,
  "keyName": "Dm"
}